zsmash/bootstrap.cpp
zsmash/utils.py
zsmash/bootstrap.pyx
zsmash/smash.pyx
zsmash/__init__.py
zsmash/smash.cpp
zsmash/bootstrap.cpython-36m-x86_64-linux-gnu.so
zsmash.libs/libgslcblas-15b2d0fe.so.0.0.0
zsmash.libs/libgsl-b885fd68.so.0.14.0
zsmash.libs/libgomp-3300acd3.so.1.0.0
zsmash-0.0.2.dist-info/LICENSE.md
zsmash-0.0.2.dist-info/top_level.txt
zsmash-0.0.2.dist-info/WHEEL
zsmash-0.0.2.dist-info/METADATA
zsmash-0.0.2.dist-info/RECORD
