Metadata-Version: 2.1
Name: zsmash
Version: 0.0.2
Summary: Cythonized Libraires of ZeD Code
Home-page: https://github.com/zeroknowledgediscovery/python_implementations_
Author: zed.uchicago.edu
Author-email: ishanu@uchicago.edu
License: LICENSE
Keywords: cython,machine learning
Platform: UNKNOWN
Classifier: Development Status :: 4 - Beta
Classifier: Intended Audience :: Developers
Classifier: Intended Audience :: Science/Research
Classifier: Topic :: Scientific/Engineering :: Information Analysis
Classifier: Topic :: Software Development :: Libraries
Classifier: License :: OSI Approved :: MIT License
Classifier: Programming Language :: Python :: 3.6
Requires-Python: >=3.6
License-File: LICENSE.md
Requires-Dist: Cython (>=0.29.23numpy)
Requires-Dist: pandas
